cp_data_structures/__init__.py
cp_data_structures/graph/__init__.py
cp_data_structures/graph/graph.py
cp_data_structures/linked_list/__init__.py
cp_data_structures/linked_list/linked_list.py
cp_data_structures/linked_list/linked_list_client.py
cp_data_structures-0.1.0.dist-info/METADATA
cp_data_structures-0.1.0.dist-info/WHEEL
cp_data_structures-0.1.0.dist-info/RECORD
